basicenum-2023.1.dist-info/METADATA
basicenum-2023.1.dist-info/WHEEL
basicenum-2023.1.dist-info/licenses/LICENSE
basicenum/__init__.py
basicenum/compat.py
basicenum-2023.1.dist-info/RECORD
