Metadata-Version: 2.1
Name: basicenum
Version: 2023.1
Summary: Simple(r) enums
Keywords: enum
Author-Email: Brett Cannon <brett@python.org>
License: Copyright 2022 Brett Cannon
Classifier: License :: OSI Approved :: BSD License
Project-URL: Repository, https://github.com/brettcannon/basicenum
Requires-Python: >=3.9
Provides-Extra: test
Provides-Extra: benchmark
Requires-Dist: pytest; extra == "test"
Requires-Dist: richbench; extra == "benchmark"
